_sql_server_lineage.cp39-win_amd64.h
_sql_server_lineage.cp39-win_amd64.pyd
sql_server_lineage.py
sql_server_lineage-1.13.0.dist-info/LICENSE
sql_server_lineage-1.13.0.dist-info/METADATA
sql_server_lineage-1.13.0.dist-info/WHEEL
sql_server_lineage-1.13.0.dist-info/top_level.txt
sql_server_lineage-1.13.0.dist-info/RECORD
