Metadata-Version: 2.1
Name: sql-server-lineage
Version: 1.13.0
Summary: Python library to extract lineage from Sql Server stored procedures
Author: Ivan Ostymchuk
License: MIT
Requires-Python: >=3.8
License-File: LICENSE
